macchanger.pyi
macchanger.cpython-39-x86_64-linux-gnu.so
macchanger1-0.0.4.dist-info/LICENSE
macchanger1-0.0.4.dist-info/WHEEL
macchanger1-0.0.4.dist-info/RECORD
macchanger1-0.0.4.dist-info/METADATA
macchanger1-0.0.4.dist-info/top_level.txt
