Metadata-Version: 2.1
Name: macchanger1
Version: 0.0.4
Summary: MAC changer
Author: skrab-sah
Author-email: skrab.sah@gmail.com
Classifier: Operating System :: POSIX :: Linux
Classifier: License :: OSI Approved :: MIT License
License-File: LICENSE
